tokenizer_xm
