Metadata-Version: 2.1
Name: tokenizer-xm
Version: 1.0.2
Summary: Tokenizing with options to include contractions, lemmatize and stem.
Home-page: https://github.com/ALaughingHorse/tokenizer_xm
Author: Xiao Ma
Author-email: Marshalma0923@gmail.com
License: MIT
Download-URL: https://github.com/ALaughingHorse/tokenizer_xm/archive/v_102.tar.gz
Keywords: text preprocessing,tokenize,NLP
Platform: UNKNOWN
Classifier: Development Status :: 3 - Alpha
Classifier: Intended Audience :: Developers
Classifier: Topic :: Software Development :: Build Tools
Classifier: License :: OSI Approved :: MIT License
Classifier: Programming Language :: Python :: 3
Classifier: Programming Language :: Python :: 3.4
Classifier: Programming Language :: Python :: 3.5
Classifier: Programming Language :: Python :: 3.6
Classifier: Programming Language :: Python :: 3.7
